cadwangpackage1/__init__.py
cadwangpackage1/__main__.py
package_name/__init__.py
package_name/__main__.py
cadwangpagckage1-0.1.dist-info/METADATA
cadwangpagckage1-0.1.dist-info/WHEEL
cadwangpagckage1-0.1.dist-info/top_level.txt
cadwangpagckage1-0.1.dist-info/RECORD
