Metadata-Version: 2.1
Name: cadwangpagckage1
Version: 0.1
Summary: Package Description
Home-page: http://example.com
License: UNKNOWN
Platform: UNKNOWN
